manimforge-0.1.2.dist-info/METADATA
manimforge-0.1.2.dist-info/WHEEL
manimforge-0.1.2.dist-info/licenses/LICENSE.md
manimforge/manimforge.pyi
manimforge/_setup.py
manimforge/__init__.py
manimforge/cairo.pyi
manimforge/manimforge.cpython-311-x86_64-linux-gnu.so
manimforge-0.1.2.dist-info/RECORD
