Metadata-Version: 2.4
Name: manimforge
Version: 0.1.2
Classifier: Programming Language :: Rust
Classifier: Programming Language :: Python :: Implementation :: CPython
Classifier: Programming Language :: Python :: Implementation :: PyPy
Classifier: Programming Language :: Python :: 3.9
Classifier: Programming Language :: Python :: 3.10
Classifier: Programming Language :: Python :: 3.11
Classifier: Programming Language :: Python :: 3.12
Classifier: Programming Language :: Python :: 3.13
Classifier: Topic :: Scientific/Engineering
Classifier: Topic :: Multimedia :: Video
Classifier: Topic :: Multimedia :: Graphics
Classifier: Development Status :: 3 - Alpha
Classifier: License :: OSI Approved :: MIT License
Classifier: Natural Language :: English
Requires-Dist: manim >0.18.0
License-File: LICENSE.md
Summary: Rust parts of the Animation Library Manim
License: MIT
Requires-Python: >=3.9
Project-URL: documentation, https://docs.manim.community/
Project-URL: homepage, https://www.manim.community/
Project-URL: repository, https://github.com/ManimCommunity/manim-forge
